{
  "id": "overview-page",
  "slug": "platform/overview",
  "meta": {
    "title": "OlonJS — Platform Overview",
    "description": "Overview of the OlonJS platform, architecture direction, and product surface."
  },
  "sections": [
    {
      "id": "doc-page-hero",
      "type": "page-hero",
      "data": {
        "breadcrumb": [
          {
            "id": "crumb-home",
            "label": "Home",
            "href": "/"
          },
          {
            "id": "crumb-platform",
            "label": "Platform",
            "href": "/platform/overview"
          }
        ],
        "badge": "",
        "title": "Platform",
        "titleItalic": "Overview",
        "description": "High-level overview of the OlonJS platform."
      }
    }
  ]
}
